Metadata-Version: 2.1
Name: pe-parser
Version: 0.1.2
Summary: PE parser implementation
Home-page: https://github.com/danielgibert/pe_parser
Author: Daniel Gibert
Author-email: danigibert24@gmail.com
License: MIT
Requires-Python: >=3.6.9
License-File: LICENSE
Requires-Dist: nltk
Requires-Dist: mahotas
Requires-Dist: matplotlib
